dashgen/__init__.py
dashgen/charts/__init__.py
dashgen/charts/chartjs.py
dashgen/core/__init__.py
dashgen/core/builder.py
dashgen/core/components.py
dashgen/core/elements.py
dashgen/core/layout.py
dashgen/core/renderer.py
dashgen/core/utils.py
dashgen/templates/base.html
dashgen/themes/default.css
dashgen-0.3.2.dist-info/licenses/LICENSE
tests/__init__.py
tests/test_builder.py
tests/test_chartjs.py
tests/test_components.py
tests/test_layout.py
tests/test_renderer.py
tests/test_utils.py
dashgen-0.3.2.dist-info/METADATA
dashgen-0.3.2.dist-info/WHEEL
dashgen-0.3.2.dist-info/top_level.txt
dashgen-0.3.2.dist-info/RECORD
