Metadata-Version: 2.4
Name: dashgen
Version: 0.3.2
Summary: Gere dashboards visuais como imagens.
Home-page: https://github.com/77-Indicadores/dashgen
Author: Vinicius Moreira
Author-email: vinicius@77indicadores.com.br
Classifier: Programming Language :: Python :: 3
Classifier: License :: OSI Approved :: MIT License
Classifier: Operating System :: OS Independent
Requires-Python: >=3.7
License-File: LICENSE
Requires-Dist: playwright
Requires-Dist: jinja2
Dynamic: author
Dynamic: author-email
Dynamic: classifier
Dynamic: description
Dynamic: description-content-type
Dynamic: home-page
Dynamic: license-file
Dynamic: requires-dist
Dynamic: requires-python
Dynamic: summary
